{
  "company_name": "Biotoscana Investments SA",
  "primary_activity": "Investimentos em saúde e biotecnologia",
  "sector": "Saúde",
  "subsector": "Biotecnologia",
  "industry": "Investimentos em empresas de biotecnologia e saúde",
  "activity_description": "A Biotoscana Investments SA atua no mercado de investimentos, focando em empresas de biotecnologia e saúde. Seu objetivo é apoiar o desenvolvimento de soluções inovadoras para a área da saúde.",
  "main_products_services": [
    "Investimentos em empresas de biotecnologia",
    "Investimentos em empresas de saúde"
  ],
  "competitors": [
    "Outras empresas de investimentos em biotecnologia e saúde"
  ],
  "economic_classification_code": "6492-8/01"
}