{
  "company_name": "Companhia Estadual de Geracao e Transmissao de Energia Eletrica CEEE GT",
  "primary_activity": "Geração e transmissão de energia elétrica",
  "sector": "Energia",
  "subsector": "Energia Elétrica",
  "industry": "Geração e Transmissão de Energia Elétrica",
  "activity_description": "A Companhia Estadual de Geração e Transmissão de Energia Elétrica CEEE GT atua na geração e transmissão de energia elétrica, fornecendo eletricidade para consumidores residenciais, comerciais e industriais.",
  "main_products_services": [
    "Energia elétrica"
  ],
  "competitors": [
    "Empresas de geração e transmissão de energia elétrica"
  ],
  "economic_classification_code": ""
}